[
  {
    "shortcut": "1C Предприятие (учебная версия)",
    "icon": "1C"
  },
  {
    "shortcut": "Adobe Photoshop",
    "icon": "Adobe Photoshop"
  },
  {
    "shortcut": "PyCharm Community Edition 2023.3.2",
    "icon": "Python"
  },
  {
    "shortcut": "FL Studio 20",
    "icon": "FL Studio"
  },
  {
    "shortcut": "MiniFuse Control Center",
    "icon": "Minifuse"
  },
  {
    "shortcut": "Visual Studio Code",
    "icon": "Visual Studio Code"
  },
  {
    "shortcut": "Discord",
    "icon": "Discord"
  },
  {
    "shortcut": "Git Bash",
    "icon": "Git"
  },
  {
    "shortcut": "MAMP",
    "icon": "MAMP"
  },
  {
    "shortcut": "NIUBI Partition Editor Free Edition",
    "icon": "NIUBI"
  },
  {
    "shortcut": "Telegram",
    "icon": "Telegram"
  },
  {
    "shortcut": "ReVoice Pro",
    "icon": "ReVoice Pro"
  },
  {
    "shortcut": "WhatsApp",
    "icon": "WhatsApp"
  },
  {
    "shortcut": "REAPER (x64)",
    "icon": "Reaper"
  },
]
